dcore/__init__.py
dcore/_dispatcher.py
dcore/_testing.py
dcore/_typing.py
dcore/_version.py
dcore/dc.py
dcore/dcore.py
dcore/dcore_anacont.py
dcore/dcore_bse.py
dcore/dcore_check.py
dcore/dcore_mpicheck.py
dcore/dcore_pre.py
dcore/dcore_spectrum.py
dcore/dcore_w90tool.py
dcore/dmft_core.py
dcore/fourier.py
dcore/interaction.py
dcore/manip_database.py
dcore/mpi.py
dcore/mpi_command.py
dcore/numdiff.py
dcore/openmx2dcore.py
dcore/option_tables.py
dcore/program_options.py
dcore/sumkdft_compat.py
dcore/sumkdft_opt.py
dcore/sumkdft_post.py
dcore/symmetrizer.py
dcore/tools.py
dcore/typed_parser.py
dcore/version.py
dcore/anacont/__init__.py
dcore/anacont/pade.py
dcore/anacont/spm.py
dcore/backend/__init__.py
dcore/backend/_triqs_mpi.py
dcore/converters/__init__.py
dcore/converters/converter_tools.py
dcore/converters/hk.py
dcore/converters/wannier90.py
dcore/impurity_solvers/__init__.py
dcore/impurity_solvers/alps_cthyb.py
dcore/impurity_solvers/alps_cthyb_seg.py
dcore/impurity_solvers/base.py
dcore/impurity_solvers/hphi.py
dcore/impurity_solvers/hphi_spectrum.py
dcore/impurity_solvers/jo_cthyb_seg.py
dcore/impurity_solvers/lanczos.py
dcore/impurity_solvers/null_solver.py
dcore/impurity_solvers/pomerol.py
dcore/impurity_solvers/scipy_sparse.py
dcore/impurity_solvers/scipy_sparse_main.py
dcore/impurity_solvers/triqs_cthyb.py
dcore/impurity_solvers/triqs_cthyb_impl.py
dcore/impurity_solvers/triqs_dep_tools.py
dcore/impurity_solvers/triqs_hubbard_I.py
dcore/impurity_solvers/triqs_hubbard_I_impl.py
dcore/lattice_models/__init__.py
dcore/lattice_models/_wannier90.py
dcore/lattice_models/base.py
dcore/lattice_models/external_model.py
dcore/lattice_models/predefined_models.py
dcore/lattice_models/tools.py
dcore/lattice_models/wannier90_model.py
dcore/sumkdft_workers/__init__.py
dcore/sumkdft_workers/all_workers.py
dcore/sumkdft_workers/bse_worker.py
dcore/sumkdft_workers/dos_worker.py
dcore/sumkdft_workers/gk_worker.py
dcore/sumkdft_workers/gloc_worker.py
dcore-4.2.0.dist-info/COPYING
dcore-4.2.0.dist-info/LICENSE
dcore-4.2.0.dist-info/METADATA
dcore-4.2.0.dist-info/WHEEL
dcore-4.2.0.dist-info/entry_points.txt
dcore-4.2.0.dist-info/top_level.txt
dcore-4.2.0.dist-info/RECORD
